api_mocker/__init__.py
api_mocker/advanced.py
api_mocker/ai_generator.py
api_mocker/analytics.py
api_mocker/auth_system.py
api_mocker/cli.py
api_mocker/config.py
api_mocker/core.py
api_mocker/dashboard.py
api_mocker/database_integration.py
api_mocker/enhanced_analytics.py
api_mocker/graphql_mock.py
api_mocker/ml_integration.py
api_mocker/mock_responses.py
api_mocker/openapi.py
api_mocker/plugins.py
api_mocker/recorder.py
api_mocker/scenarios.py
api_mocker/server.py
api_mocker/smart_matching.py
api_mocker/testing.py
api_mocker/websocket_mock.py
api_mocker-0.5.0.dist-info/licenses/LICENSE
api_mocker-0.5.0.dist-info/METADATA
api_mocker-0.5.0.dist-info/WHEEL
api_mocker-0.5.0.dist-info/entry_points.txt
api_mocker-0.5.0.dist-info/top_level.txt
api_mocker-0.5.0.dist-info/RECORD
