Metadata-Version: 2.4
Name: api-mocker
Version: 0.5.0
Summary: 🚀 The Ultimate API Development Acceleration Tool - 3000+ Downloads! Production-ready FastAPI mock server with AI-powered generation, scenario-based mocking, smart response matching, enhanced analytics, comprehensive testing framework, advanced mock response management, GraphQL mocking, WebSocket support, enterprise authentication, database integration, and machine learning capabilities.
Author-email: sherin joseph roy <sherin.joseph2217@gmail.com>
License: MIT License
Project-URL: Homepage, https://github.com/Sherin-SEF-AI/api-mocker
Project-URL: Repository, https://github.com/Sherin-SEF-AI/api-mocker.git
Project-URL: Documentation, https://github.com/Sherin-SEF-AI/api-mocker#readme
Project-URL: Bug Tracker, https://github.com/Sherin-SEF-AI/api-mocker/issues
Project-URL: Source Code, https://github.com/Sherin-SEF-AI/api-mocker
Project-URL: Download Statistics, https://pepy.tech/project/api-mocker
Project-URL: PyPI Page, https://pypi.org/project/api-mocker/
Keywords: api-mocking,mock-server,development-tools,fastapi,testing,microservices,api-testing,swagger,openapi,postman,rest-api,http-mocking,development-acceleration,api-development,backend-testing,api-simulation,mock-api,api-prototyping,integration-testing,web-development,cli,devops,analytics,rate-limiting,caching,authentication
Classifier: Development Status :: 4 - Beta
Classifier: Intended Audience :: Developers
Classifier: Intended Audience :: System Administrators
Classifier: Intended Audience :: Information Technology
Classifier: License :: OSI Approved :: MIT License
Classifier: Operating System :: OS Independent
Classifier: Programming Language :: Python :: 3
Classifier: Programming Language :: Python :: 3.8
Classifier: Programming Language :: Python :: 3.9
Classifier: Programming Language :: Python :: 3.10
Classifier: Programming Language :: Python :: 3.11
Classifier: Programming Language :: Python :: 3.12
Classifier: Topic :: Software Development :: Testing
Classifier: Topic :: Software Development :: Testing :: Mocking
Classifier: Topic :: Software Development :: Libraries :: Python Modules
Classifier: Topic :: Internet :: WWW/HTTP :: HTTP Servers
Classifier: Topic :: Software Development :: Quality Assurance
Classifier: Topic :: Software Development :: Build Tools
Classifier: Topic :: System :: Systems Administration
Classifier: Topic :: Utilities
Classifier: Framework :: FastAPI
Classifier: Framework :: Pytest
Classifier: Environment :: Web Environment
Classifier: Environment :: Console
Classifier: Typing :: Typed
Requires-Python: >=3.8
License-File: LICENSE
Requires-Dist: typer>=0.9.0
Requires-Dist: fastapi>=0.100.0
Requires-Dist: uvicorn>=0.23.0
Requires-Dist: PyYAML>=6.0
Requires-Dist: toml>=0.10.2
Requires-Dist: pytest>=7.0.0
Requires-Dist: httpx>=0.24.0
Requires-Dist: rich>=13.0.0
Requires-Dist: psutil>=5.9.0
Requires-Dist: aiofiles>=23.0.0
Requires-Dist: websockets>=11.0.0
Requires-Dist: aiosqlite>=0.19.0
Requires-Dist: asyncpg>=0.29.0
Requires-Dist: motor>=3.3.0
Requires-Dist: pymongo>=4.6.0
Requires-Dist: redis>=5.0.0
Requires-Dist: scikit-learn>=1.3.0
Requires-Dist: pandas>=2.0.0
Requires-Dist: numpy>=1.24.0
Requires-Dist: pyotp>=2.9.0
Requires-Dist: qrcode>=7.4.0
Requires-Dist: PyJWT>=2.8.0
Requires-Dist: joblib>=1.3.0
Provides-Extra: advanced
Requires-Dist: PyJWT>=2.8.0; extra == "advanced"
Requires-Dist: redis>=4.5.0; extra == "advanced"
Dynamic: license-file
